redisfile.py
setup.py
redis_file.egg-info/PKG-INFO
redis_file.egg-info/SOURCES.txt
redis_file.egg-info/dependency_links.txt
redis_file.egg-info/not-zip-safe
redis_file.egg-info/requires.txt
redis_file.egg-info/top_level.txt