Metadata-Version: 1.0
Name: redis-file
Version: 0.0.1
Summary: Write to redis as if it was a file
Home-page: https://github.com/daniellawrence/redis-file
Author: Daniel Lawrence
Author-email: dannyla@linux.com
License: UNKNOWN
Platform: UNKNOWN
